manubot_ai_editor/__init__.py
manubot_ai_editor/editor.py
manubot_ai_editor/env_vars.py
manubot_ai_editor/exceptions.py
manubot_ai_editor/model_providers.py
manubot_ai_editor/models.py
manubot_ai_editor/prompt_config.py
manubot_ai_editor/utils.py
manubot_ai_editor-0.5.5.dist-info/LICENSE.md
manubot_ai_editor-0.5.5.dist-info/METADATA
manubot_ai_editor-0.5.5.dist-info/WHEEL
manubot_ai_editor-0.5.5.dist-info/RECORD
