Metadata-Version: 2.3
Name: manubot-ai-editor
Version: 0.5.5
Summary: A Manubot plugin to revise a manuscript using GPT-3
License: BSD-3-Clause
Author: Milton Pividori
Author-email: miltondp@gmail.com
Maintainer: Milton Pividori
Requires-Python: >=3.10,<4.0
Classifier: License :: OSI Approved :: BSD License
Classifier: Operating System :: OS Independent
Classifier: Programming Language :: Python :: 3
Classifier: Programming Language :: Python :: 3.10
Classifier: Programming Language :: Python :: 3.11
Classifier: Programming Language :: Python :: 3.12
Classifier: Programming Language :: Python :: 3.13
Requires-Dist: charset-normalizer (>=3.4.1,<4.0.0)
Requires-Dist: langchain-anthropic (>=0.3.0,<0.4.0)
Requires-Dist: langchain-core (>=0.3.6,<0.4.0)
Requires-Dist: langchain-openai (>=0.2.0,<0.3.0)
Requires-Dist: pyyaml
Project-URL: Homepage, https://github.com/manubot/manubot-ai-editor
Project-URL: Repository, https://github.com/manubot/manubot-ai-editor
